Marvel_anup_anm/Marvel_activity5.py
Marvel_anup_anm/__init__.py
Marvel_anup_anm-0.1.dist-info/METADATA
Marvel_anup_anm-0.1.dist-info/WHEEL
Marvel_anup_anm-0.1.dist-info/top_level.txt
Marvel_anup_anm-0.1.dist-info/RECORD
