Metadata-Version: 2.1
Name: Marvel-anup-anm
Version: 0.1
Summary: fetch data from marvel and use filters
Home-page: UNKNOWN
Author: Anup Kumar Dey
License: UNKNOWN
Platform: UNKNOWN
